{"5h2jmTFf5l1J7uxyhaI7Kg==":"active-activity-640x427.jpg","wV+DOblthr8MNSY/HRomBQ==":"training-828726-1280-1024x680.jpg","YuHJq61rUeblR4LFRh63aA==":"active-activity-1024x683.jpg","4mL0Gd/B51FYA7/uegaWhg==":"active-beautiful-beauty-866027-1024x683.jpg","EkZ0SfK19k027e8LnInjNQ==":"class1-1024x689.jpg","ZxjlllmndB75Zv0lOPmZwQ==":"active-activity-1024x683.jpeg","K0di32hHd0XYBfedypgoOg==":"active-activity-955x637.jpg","1y7N5av3h9Po/hXwnvY2LQ==":"active-beautiful-beauty-866028-1024x683.jpg","2QjtLm827GVDUsG63E9rjQ==":"class1-1-1024x689.jpg","j9kqEWw0RXvEQ/MRcoT2bg==":"active-activity-955x637.jpeg","8WpKvIqTKUznh0d0EXZsgw==":"bright-close-up-color-221247-2000x1333.jpg","rrQcdOKJMKO5leWimeOw3Q==":"bright-close-up-color-221247-2000x1333.jpeg","GNpwMUaV/RRG1fKaUboCoA==":"active-arms-back-867453-1256x707.jpg","sTvirTK1bv6j//yB32LiBA==":"sportive-couple-626x626.jpg","BqgCW5PyhctURkc9pe1hMg==":"class4-1101x734.jpg","nZrWQLxErV8/cbPfoH5nyQ==":"people-2604149-1280-518x292.jpg","Uh/slLOYOGlQzFKK06JEVg==":"session-640x360.jpg","OaWvaiAxM/mWAiTQXVkGAA==":"session-518x291.jpg","tOTbWnJxgeW9vVO312dzgA==":"active-activity1-518x346.jpg","Ez3MZKq0ygnAfp02KOiRQw==":"active-activity1-1024x683.jpg","oKSxaq9WTy1C8u27zXwlYQ==":"people-2604149-1280-518x291.jpg","2jfG/LDzhhoad6nY3wCJLA==":"sport-2250970-640-518x345.jpg","TetRiWL92hjRvKt43WSdfQ==":"sport-2250970-640-518x345.jpeg","GeOUUUMX/9TGXggVZWFhAw==":"sport-2250970-641-518x345.jpeg","to096JuTSDQ5HPkvhWLsPA==":"woman-with-dumbbells-518x453.jpg","IWKLs9nwAY2BfRNZpcxd0Q==":"women-lifting-weights-518x345.jpg","TEfiYCNQu8DgMBgqX0cQyQ==":"active-arms-back-867453-518x345.jpg","br6ORM80U0nsfKLcmVJCVA==":"class2-518x340.jpg","n/zxR62LBH4uWBqgVdZGVQ==":"class3-518x345.jpg","ztwEZOvM6GaSvKqSqeFnFw==":"yoga-2959226-1280-518x345.jpg","HjmwiSSBsZhv2qsUe2ZoHg==":"training-828726-1280-1280x850.jpg","xlQTVRX/JXkwnLfwz7fjvw==":"healthy-woman-626x379.jpg","CAMTYGZgL6nAlST/ScykSg==":"yoga1-626x417.jpg","f6WtLJoTDNBBHZPr911q9w==":"victor-freitas-wvdydxdzkhs-unsplash-626x417.jpg","v5iOuSUS/GOZSUNHsj4u4w==":"victor-freitas-wvdydxdzkhs-unsplash-1-626x417.jpg","q9lA4HpOpRiVD71fjmC8ww==":"anastase-maragos-fp7cfyppukm-unsplash-626x417.jpg","nJswXaeDrNzn9O9Vyj9rjA==":"anastase-maragos-fp7cfyppukm-unsplash-2-626x417.jpg","p7D/2frQxEoPCs9Y1MbqTg==":"anastase-maragos-9dzwzqwzmde-unsplash-1800x1200.jpg","zCWkjgyYiBpm4FtULEzAqg==":"anastase-maragos-9dzwzqwzmde-unsplash-2-1980x1320.jpg","vsBXXkthQcXEkTq/0ZfySw==":"anastase-maragos-9dzwzqwzmde-unsplash-626x417.jpg","i1dSTjDSun9Xx+ztP4wdxg==":"victor-freitas-wvdydxdzkhs-unsplash%2022.48.19-1980x1320.jpg","h+7w6kdDjgORMoT+mIi8wg==":"cathy-pham-3jan9inapqi-unsplash-1980x1469.jpg","DOek+liX2O8cZvs7ToDXOA==":"risen-wang-20jx9b35r_m-unsplash-2000x1498.jpg","Imxp0F6bVGp7bIQpSi1Jxw==":"risen-wang-20jx9b35r_m-unsplash-2400x1798.jpg","WyCD6aWyUlb1ptq204OoDQ==":"sven-mieke-jo6vbwx9h9y-unsplash-2000x1335.jpg","luNQIRYXchPh3rdv0PTW4w==":"meditation-1187x1781.jpg","xz88I3/DJP+En/7cGUtIng==":"class2-561x368.jpg","60bYuh/PEevDWK0uUb1/2g==":"class3-561x374.jpg","vU3r/ElaIeDnE368tBXNJw==":"healthy-woman-561x340.jpg","Du2TswqyjVWOI7pZZfEE0w==":"pexels-photo-1308746-561x374.jpg","u6erGLEinWkhkprVzm08hQ==":"active-beautiful-beauty-866027-561x374.jpg","DKQpNLWvksk1JBr+43DE/g==":"active-activity-561x374.jpg","ht3xDRd1lnTjIXl7jdc45A==":"active-activity.jpg","EAq5b0DY8ccMIJf1rLYheA==":"active-activity-1.jpg","o514D56Ka+sLrBwNgi78vw==":"active-activity1.jpg","fPymLtJgbx/CgNFpB0TF2w==":"people-2604149.jpg","AVniioyxa4mFzphz54dPWA==":"class3.jpg","VCSyFgfB/o/tAcrk/AiZtg==":"sport-2250970.jpg","e8H0Ub4uikFGUUhTdJ1xHQ==":"active-beautiful-beauty-866027.jpg","cXWeHfSs9qigjB4v0hHHcw==":"active-arms-back-867453.jpg","FSvu4OG7ZoL60XSmtj9PUg==":"class4.jpg","odh1sMeuub0CMN5f7HpAvg==":"weights.png","53nUeh+mNlodINM6B8RZmA==":"001-weights.png","Q+tQ5li5ZwGciDvq0RvSoA==":"anastase-maragos-9dzwzqwzmde-unsplash.jpg","rRY+Lz/53MuvfFbLb9pT8w==":"victor-freitas-wvdydxdzkhs-unsplash-22.48.19.jpg","cebi2FNpH4LB2Sg8z9d8Fg==":"cathy-pham-3jan9inapqi-unsplash.jpg","ZNbNzIrdPtEnUjkjqb1InA==":"risen-wang-20jx9b35r-m-unsplash.jpg","OKYgUwqhXQ3Ts6iRpZKXbQ==":"w-6.jpg","28buvyTo5MG/9Pcw/Wkqsw==":"w-7.jpg","ZQIIquAzcxp1PWNpyHAuQw==":"w-10.jpg","4QwLKButfZukfZMwnieQ8g==":"w-36.jpg","OGcXAcU/GgslBXVvETdkcA==":"m-21.jpg","JtyCi0Pt/8SR2pewgPn5Vw==":"m-22.jpg","hgXEAp8zdf+0AyDQsUqYtA==":"m-28.jpg"}